tagit/__init__.py
tagit/elements.py
tagit/gen_elements.py
tagit/main.py
tagit-0.6.2.dist-info/LICENSE
tagit-0.6.2.dist-info/METADATA
tagit-0.6.2.dist-info/WHEEL
tagit-0.6.2.dist-info/RECORD
