Metadata-Version: 2.1
Name: tagit
Version: 0.6.2
Summary: HTML/SVG tag generator for minimalist
Home-page: https://github.com/hoishing/tagit
License: MIT
Keywords: template,html,svg
Author: Kelvin Ng
Author-email: hoishing@gmail.com
Requires-Python: >=3.12,<4.0
Classifier: Development Status :: 4 - Beta
Classifier: Intended Audience :: Developers
Classifier: License :: OSI Approved :: MIT License
Classifier: Programming Language :: Python :: 3
Classifier: Programming Language :: Python :: 3.12
Classifier: Topic :: Internet :: WWW/HTTP :: Dynamic Content
Project-URL: Repository, https://github.com/hoishing/tagit
